Workbook

Sheet Start Here
A1: Riverside Medical Center: Information Security Risk Assessment
A2: Risk register, control gap assessment, and vendor tiering. Riverside is a fictional organization created for a portfolio project.
A3: Assessment period: September 2026 | Methodology: NIST SP 800-30 Rev. 1 | Control frameworks: HIPAA Security Rule (45 CFR Part 164 Subpart C), NIST CSF 2.0, HHS 405(d) HICP
A5: How to use this workbook
A6: 1. Asset Register: assets and Criticality/Vulnerability scores carried over from the 'Beyond Our Walls' TPRM presentation (ESRM Steps 1-2).
A7: 2. Risk Register: each risk scored for Likelihood (1-5) and Impact (1-5). Score and rating calculate automatically. Blank rows at the bottom are ready for new risks.
A8: 3. Heat Map: counts of risks in each Likelihood x Impact cell, before (inherent) and after (residual) treatment. Updates automatically.
A9: 4. Control Gap Assessment: key safeguards mapped to HIPAA, NIST CSF 2.0, and HICP, with current implementation status.
A10: 5. Vendor Tiering: sample vendors scored on four criteria; tier and monitoring requirement calculate automatically.
A12: Legend
A13: Blue text | B13: Input you can edit (scores, statuses, text)
A14: Black text | B14: Formula: calculates automatically, do not overwrite
A15: Yellow fill | B15: Threshold settings that drive the formulas
A17: Likelihood scale (probability the risk occurs within 12 months)
A18: Score | B18: Level | C18: Definition
A19: 1 | B19: Rare | C19: Not expected; no known precedent in the sector
A20: 2 | B20: Unlikely | C20: Could occur; limited sector precedent
A21: 3 | B21: Possible | C21: Has occurred at comparable hospitals; controls partially effective
A22: 4 | B22: Likely | C22: Occurs regularly across the sector; controls weak or unverified
A23: 5 | B23: Almost Certain | C23: Actively exploited in healthcare now; no effective control in place
A25: Impact scale (worst credible effect on Riverside)
A26: Score | B26: Level | C26: Definition
A27: 1 | B27: Negligible | C27: No PHI exposure; no care disruption; cost under $10K
A28: 2 | B28: Minor | C28: Limited PHI (<500 records); brief disruption of a non-clinical function
A29: 3 | B29: Moderate | C29: Reportable breach (500+ records) or one-day disruption of a clinical or revenue function
A30: 4 | B30: Major | C30: Multi-day disruption to clinical care or revenue cycle; regulatory investigation likely
A31: 5 | B31: Severe | C31: Patient harm possible; weeks-long outage or large-scale breach; major penalties and lasting reputational damage
A33: Risk rating thresholds (Score = Likelihood x Impact)
A34: Minimum score | B34: Rating | C34: Required response
A35: 20 | B35: Critical | C35: Treat immediately; executive owner; report to board
A36: 12 | B36: High | C36: Treatment plan within 30 days; tracked by governance subcommittee
A37: 6 | B37: Medium | C37: Treat within 12 months or formally accept
A38: 1 | B38: Low | C38: Monitor; may be accepted by risk owner
A40: Vendor tier thresholds (Total of four criteria, max 12)
A41: Minimum total | B41: Tier | C41: Monitoring requirement
A42: 10 | B42: Critical | C42: Continuous monitoring + annual on-site/virtual audit + SOC 2 Type II or HITRUST
A43: 7 | B43: High | C43: Continuous monitoring + annual evidence review
A44: 4 | B44: Medium | C44: Continuous monitoring from Phase 3 + annual questionnaire
A45: 0 | B45: Low | C45: Questionnaire at onboarding and renewal

Sheet Asset Register
A1: Asset Register (ESRM Steps 1-2)
A2: Source: Criticality and Vulnerability scores (1-10) from the author's 'Beyond Our Walls' TPRM presentation, slide 5.
A4: Asset ID | B4: Asset | C4: Description | D4: Asset Owner | E4: Criticality (1-10) | F4: Vulnerability (1-10) | G4: Priority Score | H4: Priority Rank
A5: A1 | B5: Claims, Billing & Clinical Data Systems | C5: EHR, revenue-cycle, and claims/e-prescribing systems reachable through 1,300+ vendor relationships | D5: CIO | E5: 9 | F5: 9 | G5: =E5*F5 -> 81 | H5: =RANK(G5,$G$5:$G$12) -> 1
A6: A2 | B6: Controlled-Substance Inventory | C6: Opioids and benzodiazepines managed via 12 Automated Dispensing Cabinets | D6: Director of Pharmacy | E6: 9 | F6: 6 | G6: =E6*F6 -> 54 | H6: =RANK(G6,$G$5:$G$12) -> 2
A7: A3 | B7: Blood Bank & Biologics | C7: On-site blood product storage supporting surgery and trauma care | D7: Laboratory Director | E7: 7 | F7: 4 | G7: =E7*F7 -> 28 | H7: =RANK(G7,$G$5:$G$12) -> 6
A8: A4 | B8: Radioactive Materials | C8: Nuclear-medicine and oncology sealed sources and isotopes | D8: Radiation Safety Officer | E8: 8 | F8: 3 | G8: =E8*F8 -> 24 | H8: =RANK(G8,$G$5:$G$12) -> 7
A9: A5 | B9: Physical Campus & Infrastructure | C9: Power, medical gas, HVAC, and network backbone supporting the main campus | D9: VP Facilities | E9: 8 | F9: 4 | G9: =E9*F9 -> 32 | H9: =RANK(G9,$G$5:$G$12) -> 4
A10: A6 | B10: Workforce & Key Personnel | C10: Clinical staff and physicians whose availability and safety are mission-critical | D10: Chief Human Resources Officer | E10: 7 | F10: 3 | G10: =E10*F10 -> 21 | H10: =RANK(G10,$G$5:$G$12) -> 8
A11: A7 | B11: Brand Reputation & Patient Trust | C11: Community standing and patient confidence in Riverside's care | D11: Chief Communications Officer | E11: 6 | F11: 5 | G11: =E11*F11 -> 30 | H11: =RANK(G11,$G$5:$G$12) -> 5
A12: A8 | B12: Medical Device & IoT Fleet | C12: Imaging, infusion pumps, and monitors remotely serviced and patched by device vendors | D12: Director of Biomedical Engineering | E12: 7 | F12: 6 | G12: =E12*F12 -> 42 | H12: =RANK(G12,$G$5:$G$12) -> 3

Sheet Risk Register
A1: Risk Register
A2: Inherent = risk with current controls only. Residual = expected risk after the recommended controls are fully implemented. Target dates align with the TPRM program phases (Phase 1: Nov 2026, Phase 2: May 2027, Phase 3: Jan 2028).
A4: Risk ID | B4: Asset | C4: Risk Title | D4: Threat Source | E4: Vulnerability | F4: Existing Controls | G4: Likelihood (1-5) | H4: Impact (1-5) | I4: Inherent Score | J4: Inherent Rating | K4: Treatment | L4: Recommended Controls | M4: HIPAA Reference | N4: NIST CSF 2.0 | O4: Risk Owner | P4: Target Date | Q4: Residual Likelihood | R4: Residual Impact | S4: Residual Score | T4: Residual Rating | U4: Status
A5: R01 | B5: A1 | C5: Ransomware via compromised vendor remote access | D5: Ransomware affiliate (external, financially motivated) | E5: Vendor remote-access accounts not required to use MFA; access never verified at onboarding | F5: Annual BAA renewal; vendor self-attestation questionnaire | G5: 5 | H5: 5 | I5: =IF(OR(G5="",H5=""),"",G5*H5) -> 25 | J5: =IF(I5="","",IF(I5>='Start Here'!$A$35,"Critical",IF(I5>='Start Here'!$A$36,"High",IF(I5>='Start Here'!$A$37,"Medium","Low")))) -> Critical | K5: Mitigate | L5: Require phishing-resistant MFA for all vendor remote access; brokered/just-in-time vendor access; continuous monitoring of Critical-tier vendors | M5: 164.308(b)(1); 164.312(d) | N5: GV.SC; PR.AA | O5: CISO | P5: May 2027 | Q5: 2 | R5: 5 | S5: =IF(OR(Q5="",R5=""),"",Q5*R5) -> 10 | T5: =IF(S5="","",IF(S5>='Start Here'!$A$35,"Critical",IF(S5>='Start Here'!$A$36,"High",IF(S5>='Start Here'!$A$37,"Medium","Low")))) -> Medium | U5: In Progress
A6: R02 | B6: A1 | C6: Prolonged outage of claims clearinghouse halts revenue and e-prescribing | D6: Third-party service failure (ransomware or outage at vendor) | E6: Single clearinghouse with no tested failover; no manual downtime procedures for claims or e-prescribing | F6: Vendor SLA (no security or recovery terms) | G6: 4 | H6: 5 | I6: =IF(OR(G6="",H6=""),"",G6*H6) -> 20 | J6: =IF(I6="","",IF(I6>='Start Here'!$A$35,"Critical",IF(I6>='Start Here'!$A$36,"High",IF(I6>='Start Here'!$A$37,"Medium","Low")))) -> Critical | K6: Mitigate | L6: Pre-contract a secondary clearinghouse; document and drill manual downtime procedures; maintain cash-reserve plan | M6: 164.308(a)(7)(ii)(B)-(C) | N6: GV.SC; RC.RP | O6: CFO | P6: Nov 2026 | Q6: 3 | R6: 3 | S6: =IF(OR(Q6="",R6=""),"",Q6*R6) -> 9 | T6: =IF(S6="","",IF(S6>='Start Here'!$A$35,"Critical",IF(S6>='Start Here'!$A$36,"High",IF(S6>='Start Here'!$A$37,"Medium","Low")))) -> Medium | U6: In Progress
A7: R03 | B7: A1 | C7: Business Associate Agreements lack enforceable security terms | D7: Regulatory / contractual | E7: BAAs contain no minimum controls, audit rights, or breach-notification SLA | F7: Standard HIPAA BAA template | G7: 4 | H7: 4 | I7: =IF(OR(G7="",H7=""),"",G7*H7) -> 16 | J7: =IF(I7="","",IF(I7>='Start Here'!$A$35,"Critical",IF(I7>='Start Here'!$A$36,"High",IF(I7>='Start Here'!$A$37,"Medium","Low")))) -> High | K7: Mitigate | L7: Modernized BAA: MFA certification, SOC 2 Type II or HITRUST evidence, 24-hour incident notification, audit rights | M7: 164.308(b)(1); 164.314(a) | N7: GV.SC | O7: General Counsel | P7: Nov 2026 | Q7: 2 | R7: 4 | S7: =IF(OR(Q7="",R7=""),"",Q7*R7) -> 8 | T7: =IF(S7="","",IF(S7>='Start Here'!$A$35,"Critical",IF(S7>='Start Here'!$A$36,"High",IF(S7>='Start Here'!$A$37,"Medium","Low")))) -> Medium | U7: In Progress
A8: R04 | B8: A1 | C8: Compromise of a vendor's subcontractor (fourth party) | D8: External attacker targeting the vendor's supply chain | E8: No visibility into subcontractors used by Critical-tier vendors | F8: None | G8: 3 | H8: 4 | I8: =IF(OR(G8="",H8=""),"",G8*H8) -> 12 | J8: =IF(I8="","",IF(I8>='Start Here'!$A$35,"Critical",IF(I8>='Start Here'!$A$36,"High",IF(I8>='Start Here'!$A$37,"Medium","Low")))) -> High | K8: Mitigate | L8: Require Critical-tier vendors to disclose material subcontractors and flow down equivalent security requirements | M8: 164.314(a)(2)(i)(B) | N8: GV.SC | O8: Director of Procurement | P8: May 2027 | Q8: 2 | R8: 4 | S8: =IF(OR(Q8="",R8=""),"",Q8*R8) -> 8 | T8: =IF(S8="","",IF(S8>='Start Here'!$A$35,"Critical",IF(S8>='Start Here'!$A$36,"High",IF(S8>='Start Here'!$A$37,"Medium","Low")))) -> Medium | U8: Not Started
A9: R05 | B9: A1 | C9: Workforce credentials stolen through phishing | D9: Phishing campaign (external) | E9: Inconsistent MFA on webmail and EHR remote access; annual-only awareness training | F9: Email spam filter; annual HIPAA training | G9: 4 | H9: 4 | I9: =IF(OR(G9="",H9=""),"",G9*H9) -> 16 | J9: =IF(I9="","",IF(I9>='Start Here'!$A$35,"Critical",IF(I9>='Start Here'!$A$36,"High",IF(I9>='Start Here'!$A$37,"Medium","Low")))) -> High | K9: Mitigate | L9: MFA on all remote and email access; monthly phishing simulations; external-sender banners; phishing report button | M9: 164.308(a)(5); 164.312(d) | N9: PR.AA; PR.AT | O9: CISO | P9: Nov 2026 | Q9: 2 | R9: 4 | S9: =IF(OR(Q9="",R9=""),"",Q9*R9) -> 8 | T9: =IF(S9="","",IF(S9>='Start Here'!$A$35,"Critical",IF(S9>='Start Here'!$A$36,"High",IF(S9>='Start Here'!$A$37,"Medium","Low")))) -> Medium | U9: In Progress
A10: R06 | B10: A1 | C10: Ransomware spreads through unpatched internal systems | D10: Ransomware affiliate (external) | E10: Patch cycle exceeds 60 days for critical vulnerabilities; flat network segments | F10: Endpoint antivirus; monthly patch window | G10: 3 | H10: 5 | I10: =IF(OR(G10="",H10=""),"",G10*H10) -> 15 | J10: =IF(I10="","",IF(I10>='Start Here'!$A$35,"Critical",IF(I10>='Start Here'!$A$36,"High",IF(I10>='Start Here'!$A$37,"Medium","Low")))) -> High | K10: Mitigate | L10: Risk-based patching SLA (critical in 14 days); EDR on all endpoints; network segmentation of clinical systems | M10: 164.308(a)(1)(ii)(B); 164.308(a)(5)(ii)(B) | N10: ID.RA; PR.PS; PR.IR | O10: Director of IT Infrastructure | P10: May 2027 | Q10: 2 | R10: 5 | S10: =IF(OR(Q10="",R10=""),"",Q10*R10) -> 10 | T10: =IF(S10="","",IF(S10>='Start Here'!$A$35,"Critical",IF(S10>='Start Here'!$A$36,"High",IF(S10>='Start Here'!$A$37,"Medium","Low")))) -> Medium | U10: Not Started
A11: R07 | B11: A1 | C11: EHR data cannot be restored after a destructive attack | D11: Ransomware / destructive malware | E11: Backups not immutable; restore never tested end-to-end | F11: Nightly backups to on-premises storage | G11: 3 | H11: 5 | I11: =IF(OR(G11="",H11=""),"",G11*H11) -> 15 | J11: =IF(I11="","",IF(I11>='Start Here'!$A$35,"Critical",IF(I11>='Start Here'!$A$36,"High",IF(I11>='Start Here'!$A$37,"Medium","Low")))) -> High | K11: Mitigate | L11: Immutable, offline-isolated backups; quarterly restore tests with documented recovery times | M11: 164.308(a)(7)(ii)(A)-(B) | N11: PR.DS; RC.RP | O11: Director of IT Infrastructure | P11: May 2027 | Q11: 2 | R11: 4 | S11: =IF(OR(Q11="",R11=""),"",Q11*R11) -> 8 | T11: =IF(S11="","",IF(S11>='Start Here'!$A$35,"Critical",IF(S11>='Start Here'!$A$36,"High",IF(S11>='Start Here'!$A$37,"Medium","Low")))) -> Medium | U11: Not Started
A12: R08 | B12: A1 | C12: Former workforce or vendor accounts remain active | D12: Former employee, contractor, or attacker using stale credentials | E12: No automated deprovisioning; vendor accounts not tied to contract end dates | F12: Manual termination checklist | G12: 4 | H12: 4 | I12: =IF(OR(G12="",H12=""),"",G12*H12) -> 16 | J12: =IF(I12="","",IF(I12>='Start Here'!$A$35,"Critical",IF(I12>='Start Here'!$A$36,"High",IF(I12>='Start Here'!$A$37,"Medium","Low")))) -> High | K12: Mitigate | L12: Automate HR-driven deprovisioning; quarterly access reviews; vendor accounts expire with contract | M12: 164.308(a)(3)(ii)(C); 164.308(a)(4) | N12: PR.AA | O12: Director of Identity & Access | P12: Nov 2026 | Q12: 2 | R12: 3 | S12: =IF(OR(Q12="",R12=""),"",Q12*R12) -> 6 | T12: =IF(S12="","",IF(S12>='Start Here'!$A$35,"Critical",IF(S12>='Start Here'!$A$36,"High",IF(S12>='Start Here'!$A$37,"Medium","Low")))) -> Medium | U12: In Progress
A13: R09 | B13: A1 | C13: Inappropriate employee access to patient records | D13: Insider (curiosity, personal relationship, or malicious) | E13: Audit logs collected but not proactively reviewed | F13: Role-based EHR access; confidentiality agreement | G13: 4 | H13: 3 | I13: =IF(OR(G13="",H13=""),"",G13*H13) -> 12 | J13: =IF(I13="","",IF(I13>='Start Here'!$A$35,"Critical",IF(I13>='Start Here'!$A$36,"High",IF(I13>='Start Here'!$A$37,"Medium","Low")))) -> High | K13: Mitigate | L13: Automated EHR access monitoring (e.g., VIP and coworker record alerts); sanctions policy enforcement | M13: 164.312(b); 164.308(a)(1)(ii)(D) | N13: DE.CM; PR.AA | O13: Privacy Officer | P13: May 2027 | Q13: 2 | R13: 3 | S13: =IF(OR(Q13="",R13=""),"",Q13*R13) -> 6 | T13: =IF(S13="","",IF(S13>='Start Here'!$A$35,"Critical",IF(S13>='Start Here'!$A$36,"High",IF(S13>='Start Here'!$A$37,"Medium","Low")))) -> Medium | U13: Not Started
A14: R10 | B14: A8 | C14: Medical devices compromised through vendor maintenance connections | D14: External attacker or compromised device vendor | E14: Device vendors keep always-on remote access; devices on shared network; legacy OS on some imaging systems | F14: Device inventory (partial) | G14: 3 | H14: 5 | I14: =IF(OR(G14="",H14=""),"",G14*H14) -> 15 | J14: =IF(I14="","",IF(I14>='Start Here'!$A$35,"Critical",IF(I14>='Start Here'!$A$36,"High",IF(I14>='Start Here'!$A$37,"Medium","Low")))) -> High | K14: Mitigate | L14: Complete device inventory; segment medical devices; vendor remote access only through brokered, logged sessions | M14: 164.308(a)(1)(ii)(A); 164.312(a)(1) | N14: ID.AM; PR.IR; GV.SC | O14: Director of Biomedical Engineering | P14: Jan 2028 | Q14: 2 | R14: 4 | S14: =IF(OR(Q14="",R14=""),"",Q14*R14) -> 8 | T14: =IF(S14="","",IF(S14>='Start Here'!$A$35,"Critical",IF(S14>='Start Here'!$A$36,"High",IF(S14>='Start Here'!$A$37,"Medium","Low")))) -> Medium | U14: Not Started
A15: R11 | B15: A2 | C15: Controlled-substance diversion from Automated Dispensing Cabinets | D15: Insider (clinical staff) | E15: Override reports reviewed inconsistently; shared credentials on some units | F15: ADC badge + PIN access; monthly pharmacy reconciliation | G15: 3 | H15: 4 | I15: =IF(OR(G15="",H15=""),"",G15*H15) -> 12 | J15: =IF(I15="","",IF(I15>='Start Here'!$A$35,"Critical",IF(I15>='Start Here'!$A$36,"High",IF(I15>='Start Here'!$A$37,"Medium","Low")))) -> High | K15: Mitigate | L15: Diversion analytics on ADC transactions; ban shared credentials; biometric ADC login | M15: N/A (DEA / state pharmacy rules) | N15: PR.AA; DE.CM | O15: Director of Pharmacy | P15: May 2027 | Q15: 2 | R15: 3 | S15: =IF(OR(Q15="",R15=""),"",Q15*R15) -> 6 | T15: =IF(S15="","",IF(S15>='Start Here'!$A$35,"Critical",IF(S15>='Start Here'!$A$36,"High",IF(S15>='Start Here'!$A$37,"Medium","Low")))) -> Medium | U15: Not Started
A16: R12 | B16: A5 | C16: Hurricane or extended power loss disrupts campus and on-site data center | D16: Natural hazard (Gulf Coast hurricane season) | E16: Single on-site data center; generator fuel supply for ~72 hours | F16: Backup generators; emergency operations plan | G16: 3 | H16: 5 | I16: =IF(OR(G16="",H16=""),"",G16*H16) -> 15 | J16: =IF(I16="","",IF(I16>='Start Here'!$A$35,"Critical",IF(I16>='Start Here'!$A$36,"High",IF(I16>='Start Here'!$A$37,"Medium","Low")))) -> High | K16: Mitigate | L16: Secondary hosting site or cloud failover for EHR; fuel resupply contracts; annual hurricane tabletop exercise | M16: 164.308(a)(7)(ii)(B)-(C) | N16: RC.RP; ID.IM | O16: VP Facilities | P16: Jan 2028 | Q16: 3 | R16: 3 | S16: =IF(OR(Q16="",R16=""),"",Q16*R16) -> 9 | T16: =IF(S16="","",IF(S16>='Start Here'!$A$35,"Critical",IF(S16>='Start Here'!$A$36,"High",IF(S16>='Start Here'!$A$37,"Medium","Low")))) -> Medium | U16: Not Started
... A19: R15 | B19: A4 | C19: Theft or loss of radioactive sealed sources | D19: Malicious actor or insider | E19: Sources stored in controlled areas; inventory checks periodic | F19: Locked storage; NRC-required inventories; badge access | G19: 1 | H19: 5 | I19: =IF(OR(G19="",H19=""),"",G19*H19) -> 5 | J19: =IF(I19="","",IF(I19>='Start Here'!$A$35,"Critical",IF(I19>='Start Here'!$A$36,"High",IF(I19>='Start Here'!$A$37,"Medium","Low")))) -> Low | K19: Accept | L19: Maintain current NRC/state program controls; reassess annually | M19: N/A (NRC 10 CFR Part 37) | N19: PR.AA (physical) | O19: Radiation Safety Officer | P19: Annual review | Q19: 1 | R19: 5 | S19: =IF(OR(Q19="",R19=""),"",Q19*R19) -> 5 | T19: =IF(S19="","",IF(S19>='Start Here'!$A$35,"Critical",IF(S19>='Start Here'!$A$36,"High",IF(S19>='Start Here'!$A$37,"Medium","Low")))) -> Low | U19: Accepted
A20: R16 | I20: =IF(OR(G20="",H20=""),"",G20*H20) | J20: =IF(I20="","",IF(I20>='Start Here'!$A$35,"Critical",IF(I20>='Start Here'!$A$36,"High",IF(I20>='Start Here'!$A$37,"Medium","Low")))) | S20: =IF(OR(Q20="",R20=""),"",Q20*R20) | T20: =IF(S20="","",IF(S20>='Start Here'!$A$35,"Critical",IF(S20>='Start Here'!$A$36,"High",IF(S20>='Start Here'!$A$37,"Medium","Low"))))
A21: R17 | I21: =IF(OR(G21="",H21=""),"",G21*H21) | J21: =IF(I21="","",IF(I21>='Start Here'!$A$35,"Critical",IF(I21>='Start Here'!$A$36,"High",IF(I21>='Start Here'!$A$37,"Medium","Low")))) | S21: =IF(OR(Q21="",R21=""),"",Q21*R21) | T21: =IF(S21="","",IF(S21>='Start Here'!$A$35,"Critical",IF(S21>='Start Here'!$A$36,"High",IF(S21>='Start Here'!$A$37,"Medium","Low"))))
A22: R18 | I22: =IF(OR(G22="",H22=""),"",G22*H22) | J22: =IF(I22="","",IF(I22>='Start Here'!$A$35,"Critical",IF(I22>='Start Here'!$A$36,"High",IF(I22>='Start Here'!$A$37,"Medium","Low")))) | S22: =IF(OR(Q22="",R22=""),"",Q22*R22) | T22: =IF(S22="","",IF(S22>='Start Here'!$A$35,"Critical",IF(S22>='Start Here'!$A$36,"High",IF(S22>='Start Here'!$A$37,"Medium","Low"))))
A23: R19 | I23: =IF(OR(G23="",H23=""),"",G23*H23) | J23: =IF(I23="","",IF(I23>='Start Here'!$A$35,"Critical",IF(I23>='Start Here'!$A$36,"High",IF(I23>='Start Here'!$A$37,"Medium","Low")))) | S23: =IF(OR(Q23="",R23=""),"",Q23*R23) | T23: =IF(S23="","",IF(S23>='Start Here'!$A$35,"Critical",IF(S23>='Start Here'!$A$36,"High",IF(S23>='Start Here'!$A$37,"Medium","Low"))))
A24: R20 | I24: =IF(OR(G24="",H24=""),"",G24*H24) | J24: =IF(I24="","",IF(I24>='Start Here'!$A$35,"Critical",IF(I24>='Start Here'!$A$36,"High",IF(I24>='Start Here'!$A$37,"Medium","Low")))) | S24: =IF(OR(Q24="",R24=""),"",Q24*R24) | T24: =IF(S24="","",IF(S24>='Start Here'!$A$35,"Critical",IF(S24>='Start Here'!$A$36,"High",IF(S24>='Start Here'!$A$37,"Medium","Low"))))

Sheet Heat Map
A1: Risk Heat Maps
A2: Each cell counts how many risks fall at that Likelihood x Impact position. Updates automatically from the Risk Register.
A4: Inherent risk (current state) | I4: Risk count by rating
A5: Impact ↓ / Likelihood → | B5: 1 | C5: 2 | D5: 3 | E5: 4 | F5: 5 | I5: Rating | J5: Inherent | K5: Residual
A6: 5 | B6: =COUNTIFS('Risk Register'!$G$5:$G$24,B5,'Risk Register'!$H$5:$H$24,A6) -> 1 | C6: =COUNTIFS('Risk Register'!$G$5:$G$24,C5,'Risk Register'!$H$5:$H$24,A6) -> 0 | D6: =COUNTIFS('Risk Register'!$G$5:$G$24,D5,'Risk Register'!$H$5:$H$24,A6) -> 4 | E6: =COUNTIFS('Risk Register'!$G$5:$G$24,E5,'Risk Register'!$H$5:$H$24,A6) -> 1 | F6: =COUNTIFS('Risk Register'!$G$5:$G$24,F5,'Risk Register'!$H$5:$H$24,A6) -> 1 | I6: Critical | J6: =COUNTIF('Risk Register'!$J$5:$J$24,I6) -> 2 | K6: =COUNTIF('Risk Register'!$T$5:$T$24,I6) -> 0
A7: 4 | B7: =COUNTIFS('Risk Register'!$G$5:$G$24,B5,'Risk Register'!$H$5:$H$24,A7) -> 0 | C7: =COUNTIFS('Risk Register'!$G$5:$G$24,C5,'Risk Register'!$H$5:$H$24,A7) -> 0 | D7: =COUNTIFS('Risk Register'!$G$5:$G$24,D5,'Risk Register'!$H$5:$H$24,A7) -> 3 | E7: =COUNTIFS('Risk Register'!$G$5:$G$24,E5,'Risk Register'!$H$5:$H$24,A7) -> 3 | F7: =COUNTIFS('Risk Register'!$G$5:$G$24,F5,'Risk Register'!$H$5:$H$24,A7) -> 0 | I7: High | J7: =COUNTIF('Risk Register'!$J$5:$J$24,I7) -> 11 | K7: =COUNTIF('Risk Register'!$T$5:$T$24,I7) -> 0
A8: 3 | B8: =COUNTIFS('Risk Register'!$G$5:$G$24,B5,'Risk Register'!$H$5:$H$24,A8) -> 0 | C8: =COUNTIFS('Risk Register'!$G$5:$G$24,C5,'Risk Register'!$H$5:$H$24,A8) -> 0 | D8: =COUNTIFS('Risk Register'!$G$5:$G$24,D5,'Risk Register'!$H$5:$H$24,A8) -> 1 | E8: =COUNTIFS('Risk Register'!$G$5:$G$24,E5,'Risk Register'!$H$5:$H$24,A8) -> 1 | F8: =COUNTIFS('Risk Register'!$G$5:$G$24,F5,'Risk Register'!$H$5:$H$24,A8) -> 0 | I8: Medium | J8: =COUNTIF('Risk Register'!$J$5:$J$24,I8) -> 1 | K8: =COUNTIF('Risk Register'!$T$5:$T$24,I8) -> 13
A9: 2 | B9: =COUNTIFS('Risk Register'!$G$5:$G$24,B5,'Risk Register'!$H$5:$H$24,A9) -> 0 | C9: =COUNTIFS('Risk Register'!$G$5:$G$24,C5,'Risk Register'!$H$5:$H$24,A9) -> 0 | D9: =COUNTIFS('Risk Register'!$G$5:$G$24,D5,'Risk Register'!$H$5:$H$24,A9) -> 0 | E9: =COUNTIFS('Risk Register'!$G$5:$G$24,E5,'Risk Register'!$H$5:$H$24,A9) -> 0 | F9: =COUNTIFS('Risk Register'!$G$5:$G$24,F5,'Risk Register'!$H$5:$H$24,A9) -> 0 | I9: Low | J9: =COUNTIF('Risk Register'!$J$5:$J$24,I9) -> 1 | K9: =COUNTIF('Risk Register'!$T$5:$T$24,I9) -> 2
A10: 1 | B10: =COUNTIFS('Risk Register'!$G$5:$G$24,B5,'Risk Register'!$H$5:$H$24,A10) -> 0 | C10: =COUNTIFS('Risk Register'!$G$5:$G$24,C5,'Risk Register'!$H$5:$H$24,A10) -> 0 | D10: =COUNTIFS('Risk Register'!$G$5:$G$24,D5,'Risk Register'!$H$5:$H$24,A10) -> 0 | E10: =COUNTIFS('Risk Register'!$G$5:$G$24,E5,'Risk Register'!$H$5:$H$24,A10) -> 0 | F10: =COUNTIFS('Risk Register'!$G$5:$G$24,F5,'Risk Register'!$H$5:$H$24,A10) -> 0 | I10: Total | J10: =SUM(J6:J9) -> 15 | K10: =SUM(K6:K9) -> 15
I12: Average risk score
A13: Residual risk (after recommended controls) | I13: Inherent | J13: =IFERROR(AVERAGE('Risk Register'!$I$5:$I$24),0) -> 14.333333
A14: Impact ↓ / Likelihood → | B14: 1 | C14: 2 | D14: 3 | E14: 4 | F14: 5 | I14: Residual | J14: =IFERROR(AVERAGE('Risk Register'!$S$5:$S$24),0) -> 7.2666667
A15: 5 | B15: =COUNTIFS('Risk Register'!$Q$5:$Q$24,B14,'Risk Register'!$R$5:$R$24,A15) -> 1 | C15: =COUNTIFS('Risk Register'!$Q$5:$Q$24,C14,'Risk Register'!$R$5:$R$24,A15) -> 2 | D15: =COUNTIFS('Risk Register'!$Q$5:$Q$24,D14,'Risk Register'!$R$5:$R$24,A15) -> 0 | E15: =COUNTIFS('Risk Register'!$Q$5:$Q$24,E14,'Risk Register'!$R$5:$R$24,A15) -> 0 | F15: =COUNTIFS('Risk Register'!$Q$5:$Q$24,F14,'Risk Register'!$R$5:$R$24,A15) -> 0 | I15: Reduction | J15: =IFERROR(1-J14/J13,0) -> 0.49302326
A16: 4 | B16: =COUNTIFS('Risk Register'!$Q$5:$Q$24,B14,'Risk Register'!$R$5:$R$24,A16) -> 0 | C16: =COUNTIFS('Risk Register'!$Q$5:$Q$24,C14,'Risk Register'!$R$5:$R$24,A16) -> 5 | D16: =COUNTIFS('Risk Register'!$Q$5:$Q$24,D14,'Risk Register'!$R$5:$R$24,A16) -> 0 | E16: =COUNTIFS('Risk Register'!$Q$5:$Q$24,E14,'Risk Register'!$R$5:$R$24,A16) -> 0 | F16: =COUNTIFS('Risk Register'!$Q$5:$Q$24,F14,'Risk Register'!$R$5:$R$24,A16) -> 0
A17: 3 | B17: =COUNTIFS('Risk Register'!$Q$5:$Q$24,B14,'Risk Register'!$R$5:$R$24,A17) -> 0 | C17: =COUNTIFS('Risk Register'!$Q$5:$Q$24,C14,'Risk Register'!$R$5:$R$24,A17) -> 4 | D17: =COUNTIFS('Risk Register'!$Q$5:$Q$24,D14,'Risk Register'!$R$5:$R$24,A17) -> 2 | E17: =COUNTIFS('Risk Register'!$Q$5:$Q$24,E14,'Risk Register'!$R$5:$R$24,A17) -> 0 | F17: =COUNTIFS('Risk Register'!$Q$5:$Q$24,F14,'Risk Register'!$R$5:$R$24,A17) -> 0
A18: 2 | B18: =COUNTIFS('Risk Register'!$Q$5:$Q$24,B14,'Risk Register'!$R$5:$R$24,A18) -> 1 | C18: =COUNTIFS('Risk Register'!$Q$5:$Q$24,C14,'Risk Register'!$R$5:$R$24,A18) -> 0 | D18: =COUNTIFS('Risk Register'!$Q$5:$Q$24,D14,'Risk Register'!$R$5:$R$24,A18) -> 0 | E18: =COUNTIFS('Risk Register'!$Q$5:$Q$24,E14,'Risk Register'!$R$5:$R$24,A18) -> 0 | F18: =COUNTIFS('Risk Register'!$Q$5:$Q$24,F14,'Risk Register'!$R$5:$R$24,A18) -> 0
A19: 1 | B19: =COUNTIFS('Risk Register'!$Q$5:$Q$24,B14,'Risk Register'!$R$5:$R$24,A19) -> 0 | C19: =COUNTIFS('Risk Register'!$Q$5:$Q$24,C14,'Risk Register'!$R$5:$R$24,A19) -> 0 | D19: =COUNTIFS('Risk Register'!$Q$5:$Q$24,D14,'Risk Register'!$R$5:$R$24,A19) -> 0 | E19: =COUNTIFS('Risk Register'!$Q$5:$Q$24,E14,'Risk Register'!$R$5:$R$24,A19) -> 0 | F19: =COUNTIFS('Risk Register'!$Q$5:$Q$24,F14,'Risk Register'!$R$5:$R$24,A19) -> 0

Sheet Control Gap Assessment
A1: Control Gap Assessment
A2: Status reflects the assessed state in September 2026. Evidence notes describe what was reviewed or what is missing.
A4: Control ID | B4: Control | C4: HIPAA Reference | D4: NIST CSF 2.0 | E4: HHS 405(d) HICP Practice | F4: Status | G4: Evidence / Gap Notes | H4: Related Risks | I4: Priority | K4: Summary
A5: C01 | B5: Multi-factor authentication for all remote, email, and vendor access | C5: 164.312(d) | D5: PR.AA | E5: Access Management | F5: Partial | G5: MFA on VPN for employees only; vendor portals and webmail exempt | H5: R01, R05 | I5: High | K5: Implemented | L5: =COUNTIF($F$5:$F$30,K5) -> 1 | M5: =IFERROR(L5/SUM($L$5:$L$7),0) -> 0.071428571
A6: C02 | B6: Vendor inventory and risk-based tiering | C6: 164.308(b)(1); 164.308(a)(1)(ii)(A) | D6: GV.SC | E6: Cybersecurity Oversight and Governance | F6: Not Implemented | G6: Vendor list kept by Procurement for payment, not security; no tiers | H6: R01, R03, R04 | I6: High | K6: Partial | L6: =COUNTIF($F$5:$F$30,K6) -> 10 | M6: =IFERROR(L6/SUM($L$5:$L$7),0) -> 0.71428571
A7: C03 | B7: Business Associate Agreements with minimum security requirements | C7: 164.308(b)(1); 164.314(a) | D7: GV.SC | E7: Cybersecurity Oversight and Governance | F7: Partial | G7: BAAs signed for PHI vendors but use 2013 template without security terms | H7: R03 | I7: High | K7: Not Implemented | L7: =COUNTIF($F$5:$F$30,K7) -> 3 | M7: =IFERROR(L7/SUM($L$5:$L$7),0) -> 0.21428571
A8: C04 | B8: Continuous monitoring of Critical- and High-tier vendors | C8: 164.308(a)(1)(ii)(D) | D8: DE.CM; GV.SC | E8: Cybersecurity Oversight and Governance | F8: Not Implemented | G8: Annual self-attestation questionnaire only | H8: R01, R04 | I8: High | K8: Total | L8: =SUM(L5:L7) -> 14
A9: C05 | B9: Security awareness training and phishing simulation | C9: 164.308(a)(5) | D9: PR.AT | E9: Email Protection | F9: Partial | G9: Annual HIPAA module completed by 91% of staff; no phishing simulations | H9: R05 | I9: Medium
A10: C06 | B10: Risk-based vulnerability and patch management | C10: 164.308(a)(1)(ii)(B) | D10: ID.RA; PR.PS | E10: Vulnerability Management | F10: Partial | G10: Monthly patching; median 63 days to remediate critical findings | H10: R06 | I10: High
A11: C07 | B11: Immutable backups with tested restoration | C11: 164.308(a)(7)(ii)(A) | D11: PR.DS; RC.RP | E11: Data Protection and Loss Prevention | F11: Partial | G11: Nightly backups exist; no immutable copy; last full restore test: never | H11: R07 | I11: High
A12: C08 | B12: Contingency and downtime procedures (incl. third-party outages) | C12: 164.308(a)(7)(ii)(B)-(C) | D12: RC.RP | E12: Security Operations Center and Incident Response | F12: Not Implemented | G12: No manual procedures for claims or e-prescribing downtime | H12: R02, R12 | I12: High
A13: C09 | B13: Access provisioning, deprovisioning, and periodic review | C13: 164.308(a)(3)(ii)(C); 164.308(a)(4) | D13: PR.AA | E13: Access Management | F13: Partial | G13: Manual termination checklist; 47 active accounts found for departed staff in sample | H13: R08 | I13: High
A14: C10 | B14: Audit log review and EHR access monitoring | C14: 164.312(b) | D14: DE.CM | E14: Security Operations Center and Incident Response | F14: Partial | G14: Logs retained 1 year; reviewed only after complaints | H14: R09 | I14: Medium
A15: C11 | B15: Medical device inventory and network segmentation | C15: 164.308(a)(1)(ii)(A); 164.312(a)(1) | D15: ID.AM; PR.IR | E15: Network Connected Medical Devices | F15: Partial | G15: Inventory ~70% complete; devices share clinical VLANs | H15: R10 | I15: Medium
A16: C12 | B16: Incident response plan covering third-party incidents | C16: 164.308(a)(6) | D16: RS.MA; RS.CO | E16: Security Operations Center and Incident Response | F16: Partial | G16: Internal IR plan exists; no vendor playbook; last tabletop 2023 | H16: R13 | I16: Medium
A17: C13 | B17: Endpoint encryption and device management | C17: 164.312(a)(2)(iv) | D17: PR.DS | E17: Endpoint Protection | F17: Partial | G17: Encryption on ~85% of laptops; not enforced by policy | H17: R14 | I17: Medium
A18: C14 | B18: Enterprise risk analysis performed and documented annually | C18: 164.308(a)(1)(ii)(A) | D18: ID.RA; GV.RM | E18: Cybersecurity Oversight and Governance | F18: Implemented | G18: This assessment; to be repeated annually by the Vendor Risk Governance Subcommittee | H18: All | I18: Low

Sheet Vendor Tiering
A1: Vendor Tiering (sample of Critical-path and representative vendors)
A2: Score each criterion 0-3 (0 = none, 3 = extensive). 'Critical by default' = Yes forces Critical tier (clearinghouse and EHR vendors, per the TPRM program design). Vendor names are generic placeholders.
A4: Vendor ID | B4: Vendor (generic) | C4: Service Provided | D4: PHI Access (0-3) | E4: System Integration (0-3) | F4: Operational Criticality (0-3) | G4: Remote Access (0-3) | H4: Total (0-12) | I4: Critical by Default? | J4: Tier | K4: Monitoring Requirement | L4: BAA Required?
A5: V01 | B5: Claims Clearinghouse | C5: Claims submission, prior authorization, e-prescribing routing | D5: 3 | E5: 3 | F5: 3 | G5: 3 | H5: =IF(COUNT(D5:G5)=0,"",SUM(D5:G5)) -> 12 | I5: Yes | J5: =IF(H5="","",IF(I5="Yes","Critical",IF(H5>='Start Here'!$A$42,"Critical",IF(H5>='Start Here'!$A$43,"High",IF(H5>='Start Here'!$A$44,"Medium","Low"))))) -> Critical | K5: =IF(J5="","",INDEX('Start Here'!$C$42:$C$45,MATCH(J5,'Start Here'!$B$42:$B$45,0))) -> Continuous monitoring + annual on-site/virtual audit + SOC 2 Type II or HITRUST | L5: =IF(D5="","",IF(D5>0,"Yes","No")) -> Yes
A6: V02 | B6: EHR Platform Vendor | C6: Electronic health record hosting and support | D6: 3 | E6: 3 | F6: 3 | G6: 3 | H6: =IF(COUNT(D6:G6)=0,"",SUM(D6:G6)) -> 12 | I6: Yes | J6: =IF(H6="","",IF(I6="Yes","Critical",IF(H6>='Start Here'!$A$42,"Critical",IF(H6>='Start Here'!$A$43,"High",IF(H6>='Start Here'!$A$44,"Medium","Low"))))) -> Critical | K6: =IF(J6="","",INDEX('Start Here'!$C$42:$C$45,MATCH(J6,'Start Here'!$B$42:$B$45,0))) -> Continuous monitoring + annual on-site/virtual audit + SOC 2 Type II or HITRUST | L6: =IF(D6="","",IF(D6>0,"Yes","No")) -> Yes
A7: V03 | B7: Revenue Cycle Outsourcer | C7: Coding, billing, and denial management | D7: 3 | E7: 2 | F7: 3 | G7: 2 | H7: =IF(COUNT(D7:G7)=0,"",SUM(D7:G7)) -> 10 | I7: No | J7: =IF(H7="","",IF(I7="Yes","Critical",IF(H7>='Start Here'!$A$42,"Critical",IF(H7>='Start Here'!$A$43,"High",IF(H7>='Start Here'!$A$44,"Medium","Low"))))) -> Critical | K7: =IF(J7="","",INDEX('Start Here'!$C$42:$C$45,MATCH(J7,'Start Here'!$B$42:$B$45,0))) -> Continuous monitoring + annual on-site/virtual audit + SOC 2 Type II or HITRUST | L7: =IF(D7="","",IF(D7>0,"Yes","No")) -> Yes
A8: V04 | B8: Dispensing Cabinet Vendor | C8: Automated Dispensing Cabinets and pharmacy software | D8: 2 | E8: 2 | F8: 3 | G8: 3 | H8: =IF(COUNT(D8:G8)=0,"",SUM(D8:G8)) -> 10 | I8: No | J8: =IF(H8="","",IF(I8="Yes","Critical",IF(H8>='Start Here'!$A$42,"Critical",IF(H8>='Start Here'!$A$43,"High",IF(H8>='Start Here'!$A$44,"Medium","Low"))))) -> Critical | K8: =IF(J8="","",INDEX('Start Here'!$C$42:$C$45,MATCH(J8,'Start Here'!$B$42:$B$45,0))) -> Continuous monitoring + annual on-site/virtual audit + SOC 2 Type II or HITRUST | L8: =IF(D8="","",IF(D8>0,"Yes","No")) -> Yes
A9: V05 | B9: Imaging / PACS Vendor | C9: Picture archiving system and remote support | D9: 2 | E9: 2 | F9: 2 | G9: 3 | H9: =IF(COUNT(D9:G9)=0,"",SUM(D9:G9)) -> 9 | I9: No | J9: =IF(H9="","",IF(I9="Yes","Critical",IF(H9>='Start Here'!$A$42,"Critical",IF(H9>='Start Here'!$A$43,"High",IF(H9>='Start Here'!$A$44,"Medium","Low"))))) -> High | K9: =IF(J9="","",INDEX('Start Here'!$C$42:$C$45,MATCH(J9,'Start Here'!$B$42:$B$45,0))) -> Continuous monitoring + annual evidence review | L9: =IF(D9="","",IF(D9>0,"Yes","No")) -> Yes
A10: V06 | B10: Infusion Pump Manufacturer | C10: Pump fleet, drug library updates, remote patching | D10: 1 | E10: 2 | F10: 3 | G10: 3 | H10: =IF(COUNT(D10:G10)=0,"",SUM(D10:G10)) -> 9 | I10: No | J10: =IF(H10="","",IF(I10="Yes","Critical",IF(H10>='Start Here'!$A$42,"Critical",IF(H10>='Start Here'!$A$43,"High",IF(H10>='Start Here'!$A$44,"Medium","Low"))))) -> High | K10: =IF(J10="","",INDEX('Start Here'!$C$42:$C$45,MATCH(J10,'Start Here'!$B$42:$B$45,0))) -> Continuous monitoring + annual evidence review | L10: =IF(D10="","",IF(D10>0,"Yes","No")) -> Yes
A11: V07 | B11: Cloud Backup Provider | C11: Offsite backup storage for clinical systems | D11: 3 | E11: 2 | F11: 3 | G11: 1 | H11: =IF(COUNT(D11:G11)=0,"",SUM(D11:G11)) -> 9 | I11: No | J11: =IF(H11="","",IF(I11="Yes","Critical",IF(H11>='Start Here'!$A$42,"Critical",IF(H11>='Start Here'!$A$43,"High",IF(H11>='Start Here'!$A$44,"Medium","Low"))))) -> High | K11: =IF(J11="","",INDEX('Start Here'!$C$42:$C$45,MATCH(J11,'Start Here'!$B$42:$B$45,0))) -> Continuous monitoring + annual evidence review | L11: =IF(D11="","",IF(D11>0,"Yes","No")) -> Yes
A12: V08 | B12: Building Automation Contractor | C12: HVAC and building management systems | D12: 0 | E12: 2 | F12: 2 | G12: 3 | H12: =IF(COUNT(D12:G12)=0,"",SUM(D12:G12)) -> 7 | I12: No | J12: =IF(H12="","",IF(I12="Yes","Critical",IF(H12>='Start Here'!$A$42,"Critical",IF(H12>='Start Here'!$A$43,"High",IF(H12>='Start Here'!$A$44,"Medium","Low"))))) -> High | K12: =IF(J12="","",INDEX('Start Here'!$C$42:$C$45,MATCH(J12,'Start Here'!$B$42:$B$45,0))) -> Continuous monitoring + annual evidence review | L12: =IF(D12="","",IF(D12>0,"Yes","No")) -> No
A13: V09 | B13: Medical Transcription Service | C13: Dictation transcription for physicians | D13: 3 | E13: 1 | F13: 1 | G13: 1 | H13: =IF(COUNT(D13:G13)=0,"",SUM(D13:G13)) -> 6 | I13: No | J13: =IF(H13="","",IF(I13="Yes","Critical",IF(H13>='Start Here'!$A$42,"Critical",IF(H13>='Start Here'!$A$43,"High",IF(H13>='Start Here'!$A$44,"Medium","Low"))))) -> Medium | K13: =IF(J13="","",INDEX('Start Here'!$C$42:$C$45,MATCH(J13,'Start Here'!$B$42:$B$45,0))) -> Continuous monitoring from Phase 3 + annual questionnaire | L13: =IF(D13="","",IF(D13>0,"Yes","No")) -> Yes
A14: V10 | B14: Collections Agency | C14: Patient account collections | D14: 2 | E14: 1 | F14: 1 | G14: 0 | H14: =IF(COUNT(D14:G14)=0,"",SUM(D14:G14)) -> 4 | I14: No | J14: =IF(H14="","",IF(I14="Yes","Critical",IF(H14>='Start Here'!$A$42,"Critical",IF(H14>='Start Here'!$A$43,"High",IF(H14>='Start Here'!$A$44,"Medium","Low"))))) -> Medium | K14: =IF(J14="","",INDEX('Start Here'!$C$42:$C$45,MATCH(J14,'Start Here'!$B$42:$B$45,0))) -> Continuous monitoring from Phase 3 + annual questionnaire | L14: =IF(D14="","",IF(D14>0,"Yes","No")) -> Yes
A15: V11 | B15: Clinical Staffing Agency | C15: Travel nurse and locum placement (placed staff are treated as workforce, not a Business Associate) | D15: 0 | E15: 0 | F15: 2 | G15: 0 | H15: =IF(COUNT(D15:G15)=0,"",SUM(D15:G15)) -> 2 | I15: No | J15: =IF(H15="","",IF(I15="Yes","Critical",IF(H15>='Start Here'!$A$42,"Critical",IF(H15>='Start Here'!$A$43,"High",IF(H15>='Start Here'!$A$44,"Medium","Low"))))) -> Low | K15: =IF(J15="","",INDEX('Start Here'!$C$42:$C$45,MATCH(J15,'Start Here'!$B$42:$B$45,0))) -> Questionnaire at onboarding and renewal | L15: =IF(D15="","",IF(D15>0,"Yes","No")) -> No
A16: V12 | B16: Linen & Laundry Service | C16: Linen supply and laundering | D16: 0 | E16: 0 | F16: 1 | G16: 0 | H16: =IF(COUNT(D16:G16)=0,"",SUM(D16:G16)) -> 1 | I16: No | J16: =IF(H16="","",IF(I16="Yes","Critical",IF(H16>='Start Here'!$A$42,"Critical",IF(H16>='Start Here'!$A$43,"High",IF(H16>='Start Here'!$A$44,"Medium","Low"))))) -> Low | K16: =IF(J16="","",INDEX('Start Here'!$C$42:$C$45,MATCH(J16,'Start Here'!$B$42:$B$45,0))) -> Questionnaire at onboarding and renewal | L16: =IF(D16="","",IF(D16>0,"Yes","No")) -> No
A17: V13 | B17: Food Service Contractor | C17: Cafeteria and patient meal service | D17: 0 | E17: 0 | F17: 1 | G17: 0 | H17: =IF(COUNT(D17:G17)=0,"",SUM(D17:G17)) -> 1 | I17: No | J17: =IF(H17="","",IF(I17="Yes","Critical",IF(H17>='Start Here'!$A$42,"Critical",IF(H17>='Start Here'!$A$43,"High",IF(H17>='Start Here'!$A$44,"Medium","Low"))))) -> Low | K17: =IF(J17="","",INDEX('Start Here'!$C$42:$C$45,MATCH(J17,'Start Here'!$B$42:$B$45,0))) -> Questionnaire at onboarding and renewal | L17: =IF(D17="","",IF(D17>0,"Yes","No")) -> No
H18: =IF(COUNT(D18:G18)=0,"",SUM(D18:G18)) | J18: =IF(H18="","",IF(I18="Yes","Critical",IF(H18>='Start Here'!$A$42,"Critical",IF(H18>='Start Here'!$A$43,"High",IF(H18>='Start Here'!$A$44,"Medium","Low"))))) | K18: =IF(J18="","",INDEX('Start Here'!$C$42:$C$45,MATCH(J18,'Start Here'!$B$42:$B$45,0))) | L18: =IF(D18="","",IF(D18>0,"Yes","No"))
H19: =IF(COUNT(D19:G19)=0,"",SUM(D19:G19)) | J19: =IF(H19="","",IF(I19="Yes","Critical",IF(H19>='Start Here'!$A$42,"Critical",IF(H19>='Start Here'!$A$43,"High",IF(H19>='Start Here'!$A$44,"Medium","Low"))))) | K19: =IF(J19="","",INDEX('Start Here'!$C$42:$C$45,MATCH(J19,'Start Here'!$B$42:$B$45,0))) | L19: =IF(D19="","",IF(D19>0,"Yes","No"))
H20: =IF(COUNT(D20:G20)=0,"",SUM(D20:G20)) | J20: =IF(H20="","",IF(I20="Yes","Critical",IF(H20>='Start Here'!$A$42,"Critical",IF(H20>='Start Here'!$A$43,"High",IF(H20>='Start Here'!$A$44,"Medium","Low"))))) | K20: =IF(J20="","",INDEX('Start Here'!$C$42:$C$45,MATCH(J20,'Start Here'!$B$42:$B$45,0))) | L20: =IF(D20="","",IF(D20>0,"Yes","No"))
H21: =IF(COUNT(D21:G21)=0,"",SUM(D21:G21)) | J21: =IF(H21="","",IF(I21="Yes","Critical",IF(H21>='Start Here'!$A$42,"Critical",IF(H21>='Start Here'!$A$43,"High",IF(H21>='Start Here'!$A$44,"Medium","Low"))))) | K21: =IF(J21="","",INDEX('Start Here'!$C$42:$C$45,MATCH(J21,'Start Here'!$B$42:$B$45,0))) | L21: =IF(D21="","",IF(D21>0,"Yes","No"))
H22: =IF(COUNT(D22:G22)=0,"",SUM(D22:G22)) | J22: =IF(H22="","",IF(I22="Yes","Critical",IF(H22>='Start Here'!$A$42,"Critical",IF(H22>='Start Here'!$A$43,"High",IF(H22>='Start Here'!$A$44,"Medium","Low"))))) | K22: =IF(J22="","",INDEX('Start Here'!$C$42:$C$45,MATCH(J22,'Start Here'!$B$42:$B$45,0))) | L22: =IF(D22="","",IF(D22>0,"Yes","No"))
A24: Tier summary
A25: Critical | B25: =COUNTIF($J$5:$J$22,A25) -> 4
A26: High | B26: =COUNTIF($J$5:$J$22,A26) -> 4
A27: Medium | B27: =COUNTIF($J$5:$J$22,A27) -> 2
A28: Low | B28: =COUNTIF($J$5:$J$22,A28) -> 3
